llama_index/llms/xinference/__init__.py
llama_index/llms/xinference/base.py
llama_index/llms/xinference/utils.py
llama_index_llms_xinference-0.4.1.dist-info/METADATA
llama_index_llms_xinference-0.4.1.dist-info/WHEEL
llama_index_llms_xinference-0.4.1.dist-info/licenses/LICENSE
llama_index_llms_xinference-0.4.1.dist-info/RECORD
